terraform_aws_example_slow126/__init__.py
terraform_aws_example_slow126/docker_test.py
terraform_aws_example_slow126/main.py
terraform_aws_example_slow126-0.0.2.dist-info/METADATA
terraform_aws_example_slow126-0.0.2.dist-info/WHEEL
terraform_aws_example_slow126-0.0.2.dist-info/licenses/LICENSE
terraform_aws_example_slow126-0.0.2.dist-info/RECORD
