Metadata-Version: 2.3
Name: terraform-aws-example-slow126
Version: 0.0.2
Summary: A small example package for terraform on aws
Project-URL: Homepage, https://github.com/pypa/sampleproject
Project-URL: Issues, https://github.com/pypa/sampleproject/issues
Author-email: Spencer Low <spencerlow126@gmail.com>
License-File: LICENSE
Classifier: License :: OSI Approved :: MIT License
Classifier: Operating System :: OS Independent
Classifier: Programming Language :: Python :: 3
Requires-Python: >=3.8
